pipenv_tools_hook/__init__.py
pipenv_tools_hook-0.1.3.dist-info/METADATA
pipenv_tools_hook-0.1.3.dist-info/WHEEL
pipenv_tools_hook-0.1.3.dist-info/entry_points.txt
pipenv_tools_hook-0.1.3.dist-info/licenses/LICENSE
pipenv_tools_hook-0.1.3.dist-info/RECORD
