Metadata-Version: 2.4
Name: pipenv-tools-hook
Version: 0.1.3
Summary: A pre-commit hook for running Python tools in multiple Pipenv environments
Project-URL: Homepage, https://github.com/macieyng/pipenv-tools-hook
Project-URL: Repository, https://github.com/macieyng/pipenv-tools-hook.git
Project-URL: Issues, https://github.com/macieyng/pipenv-tools-hook/issues
Author-email: Maciej Nachtygal <maciej.nachtygal@gmail.com>
License-Expression: MIT
License-File: LICENSE
Classifier: License :: OSI Approved :: MIT License
Classifier: Operating System :: OS Independent
Classifier: Programming Language :: Python :: 3
Classifier: Programming Language :: Python :: 3.8
Classifier: Programming Language :: Python :: 3.9
Classifier: Programming Language :: Python :: 3.10
Classifier: Programming Language :: Python :: 3.11
Classifier: Programming Language :: Python :: 3.12
Requires-Python: >=3.8
Requires-Dist: pipenv>=2023.0
